jupyterlitexblock/__init__.py
jupyterlitexblock/jupyterlitexblock.py
jupyterlitexblock/storage.py
jupyterlitexblock/locale/ar/LC_MESSAGES/django.mo
jupyterlitexblock/locale/ar/LC_MESSAGES/django.po
jupyterlitexblock/static/css/jupyterlitexblock.css
jupyterlitexblock/static/html/jupyterlitexblock.html
jupyterlitexblock/static/html/upload.html
jupyterlitexblock/static/js/src/jupyterlitexblock.js
jupyterlite_xblock-16.0.8.dist-info/LICENSE
jupyterlite_xblock-16.0.8.dist-info/METADATA
jupyterlite_xblock-16.0.8.dist-info/WHEEL
jupyterlite_xblock-16.0.8.dist-info/entry_points.txt
jupyterlite_xblock-16.0.8.dist-info/top_level.txt
jupyterlite_xblock-16.0.8.dist-info/RECORD
