Metadata-Version: 2.1
Name: jupyterlite-xblock
Version: 16.0.8
Summary: Jupyterlite XBlock to embed jupyterlite service inside open edX
License: AGPL v3
License-File: LICENSE
Requires-Dist: XBlock
